[
	{
		"name": "index",
		"text": ["HOME"],
		"url": []
	},
	{
		"name": "news",
		"text": ["HOME","NEWS"],
		"url": ["../"]
	},
	{
		"name": "service",
		"text": ["HOME","SERVICE"],
		"url": ["../"]
	},
	{
		"name": "works",
		"text": ["HOME","WORKS"],
		"url": ["../"]
	},
	{
		"name": "company",
		"text": ["HOME","COMPANY"],
		"url": ["../"]
	},
	{
		"name": "recruit",
		"text": ["HOME","RECRUIT"],
		"url": ["../"]
	},
	{
		"name": "contact",
		"text": ["HOME","CONTACT"],
		"url": ["../"]
	},
	{
		"name": "news-article",
		"text": ["HOME","NEWS","WEBデザインニュースサイト「ウェブマガジン」に取材いただきました"],
		"url": ["../","/news/"]
	}
]